pacswg/__init__.py
pacswg/timer.py
pacswg/wg.py
pacswg-0.1.16.dist-info/LICENSE
pacswg-0.1.16.dist-info/METADATA
pacswg-0.1.16.dist-info/WHEEL
pacswg-0.1.16.dist-info/top_level.txt
pacswg-0.1.16.dist-info/RECORD
