Metadata-Version: 2.1
Name: pacswg
Version: 0.1.16
Summary: A workload generator made in PACS lab in York University.
Home-page: https://github.com/nimamahmoudi/pacswg
Author: Nima Mahmoudi
Author-email: nima_mahmoudi@live.com
License: UNKNOWN
Platform: UNKNOWN
Classifier: Development Status :: 4 - Beta
Classifier: Programming Language :: Python
Classifier: Programming Language :: Python :: 3
Classifier: Programming Language :: Python :: 3.6
Classifier: Intended Audience :: Developers
Classifier: License :: OSI Approved :: MIT License
Classifier: Operating System :: OS Independent
Requires-Dist: certifi (>=2019.11.28)
Requires-Dist: chardet (>=3.0.4)
Requires-Dist: idna (>=2.8)
Requires-Dist: numpy (>=1.18.1)
Requires-Dist: pandas (>=0.25.3)
Requires-Dist: python-dateutil (>=2.8.1)
Requires-Dist: pytz (>=2019.3)
Requires-Dist: requests (>=2.22.0)
Requires-Dist: six (>=1.14.0)
Requires-Dist: urllib3 (>=1.25.7)
